MANIFEST.in
README.txt
setup.cfg
setup.py
collective/__init__.py
collective.plonebookmarklets.egg-info/PKG-INFO
collective.plonebookmarklets.egg-info/SOURCES.txt
collective.plonebookmarklets.egg-info/dependency_links.txt
collective.plonebookmarklets.egg-info/entry_points.txt
collective.plonebookmarklets.egg-info/namespace_packages.txt
collective.plonebookmarklets.egg-info/not-zip-safe
collective.plonebookmarklets.egg-info/requires.txt
collective.plonebookmarklets.egg-info/top_level.txt
collective/plonebookmarklets/HISTORY.txt
collective/plonebookmarklets/INSTALL.txt
collective/plonebookmarklets/LICENSE.GPL
collective/plonebookmarklets/LICENSE.ZPL
collective/plonebookmarklets/LICENSE.txt
collective/plonebookmarklets/README.txt
collective/plonebookmarklets/TODO.txt
collective/plonebookmarklets/__init__.py
collective/plonebookmarklets/config.py
collective/plonebookmarklets/configure.zcml
collective/plonebookmarklets/interfaces.py
collective/plonebookmarklets/refresh.txt
collective/plonebookmarklets/setupHandlers.py
collective/plonebookmarklets/tool.gif
collective/plonebookmarklets/version.txt
collective/plonebookmarklets/browser/__init__.py
collective/plonebookmarklets/browser/bookmarklets.pt
collective/plonebookmarklets/browser/bookmarklets_document_actions.pt
collective/plonebookmarklets/browser/configure.zcml
collective/plonebookmarklets/browser/controlpanel.py
collective/plonebookmarklets/browser/viewlets.py
collective/plonebookmarklets/browser/images/bookmarklets.gif
collective/plonebookmarklets/locales/PloneBookmarklets.pot
collective/plonebookmarklets/locales/af/LC_MESSAGES/PloneBookmarklets.po
collective/plonebookmarklets/locales/ar/LC_MESSAGES/PloneBookmarklets.po
collective/plonebookmarklets/locales/bn/LC_MESSAGES/PloneBookmarklets.po
collective/plonebookmarklets/locales/ca/LC_MESSAGES/PloneBookmarklets.po
collective/plonebookmarklets/locales/de/LC_MESSAGES/PloneBookmarklets.po
collective/plonebookmarklets/locales/en/LC_MESSAGES/PloneBookmarklets.po
collective/plonebookmarklets/locales/es/LC_MESSAGES/PloneBookmarklets.mo
collective/plonebookmarklets/locales/es/LC_MESSAGES/PloneBookmarklets.po
collective/plonebookmarklets/locales/fr/LC_MESSAGES/PloneBookmarklets.po
collective/plonebookmarklets/locales/hi/LC_MESSAGES/PloneBookmarklets.po
collective/plonebookmarklets/locales/hu/LC_MESSAGES/PloneBookmarklets.po
