Metadata-Version: 1.1
Name: collective.plonebookmarklets
Version: 3.2
Summary: This product installs an 'Add Bookmarklet' document_action to your Plone site
Home-page: http://plone.org/products/plonebookmarklets
Author: enPraxis
Author-email: info@enpraxis.net
License: GPL
Keywords: tagging bookmarklets social bookmarking
Platform: UNKNOWN
Classifier: Framework :: Plone
Classifier: Programming Language :: Python
Classifier: Topic :: Software Development :: Libraries :: Python Modules
